jetha_cli/src/__init__.py
jetha_cli-0.1.1.dist-info/METADATA
jetha_cli-0.1.1.dist-info/WHEEL
jetha_cli-0.1.1.dist-info/entry_points.txt
jetha_cli-0.1.1.dist-info/RECORD
