Metadata-Version: 2.1
Name: jetha-cli
Version: 0.1.1
Summary: 
Home-page: https://github.com/zeel-codder/jetha-cli
Author: zeel-codder
Author-email: zeelprajapati321@gmail.com
Requires-Python: >=3.11,<4.0
Classifier: Programming Language :: Python :: 3
Classifier: Programming Language :: Python :: 3.11
Classifier: Programming Language :: Python :: 3.12
Requires-Dist: click (>=8.1.7,<9.0.0)
Requires-Dist: rich (>=13.7.0,<14.0.0)
